rkwebutil/__init__.py
rkwebutil/_version.py
rkwebutil/config.py
rkwebutil/rkauth_client.py
rkwebutil/rkauth_flask.py
rkwebutil/rkauth_webpy.py
rkwebutil/rkwebutil.py
rkwebutil/static/resetpasswd_start.js
rkwebutil/static/rkauth.js
rkwebutil/static/rkwebutil.js
rkwebutil/static/svgplot.css
rkwebutil/static/svgplot.js
rkwebutil-2.4.0.dist-info/licenses/LICENSE
rkwebutil-2.4.0.dist-info/METADATA
rkwebutil-2.4.0.dist-info/WHEEL
rkwebutil-2.4.0.dist-info/top_level.txt
rkwebutil-2.4.0.dist-info/RECORD
