Metadata-Version: 2.4
Name: rkwebutil
Version: 2.4.0
Summary: Rob Knop's Personal Web Utilities
Author: Rob Knop
Maintainer-email: Rob Knop <rknop@pobox.com>
Project-URL: repository, https://github.com/rknop/rkwebutil
Classifier: Development Status :: 4 - Beta
Classifier: Programming Language :: Python
Requires-Python: >3.11
License-File: LICENSE
Requires-Dist: dateutils<0.7.0,>=0.6.12
Requires-Dist: pycryptodome<4.0,>=3.20
Requires-Dist: pytz>=2022.7.1
Requires-Dist: pyyaml<7.0.0,>=6.0.2
Requires-Dist: requests<3.0,>=2.28
Provides-Extra: test
Requires-Dist: psycopg<4.0.0,>=3.2.0; extra == "test"
Requires-Dist: pytest; extra == "test"
Requires-Dist: remote-pdb; extra == "test"
Requires-Dist: selenium; extra == "test"
Requires-Dist: selenium_firefox; extra == "test"
Dynamic: license-file
